{
    "__default__" :
    {
        "gres": "",
	    "oversubscribe": "",
        "cpus-per-task": ""
    },

    "httrack_download" :
    {
        "oversubscribe": "-s"
    },
    
    "docalign_translate_nmt" :
    {
        "gres": "--gres gpu:tesla:1",
        "cpus-per-task": "--cpus-per-task 8"
    },

    "docalign_translate_smt" :
    {
        "cpus-per-task": "--cpus-per-task 8"
    },

    "docalign_custom_translate" :
    {
        "cpus-per-task": "--cpus-per-task 8"
    },

    "train_nmt_with_crawl_data":
    {
        "gres": "--gres gpu:tesla:1"
    },

    "train_nmt_all":
    {
        "gres": "--gres gpu:tesla:1"
    },
    
    "train_nmt":
    {
        "gres": "--gres gpu:tesla:1"
    },
    
    "translate_test":
    {
        "gres": "--gres gpu:tesla:1"
    }

}
